trytond/modules/health_stock/COPYING
trytond/modules/health_stock/MANIFEST.in
trytond/modules/health_stock/README.rst
trytond/modules/health_stock/__init__.py
trytond/modules/health_stock/data/messages/messages.xml
trytond/modules/health_stock/doc/index.rst
trytond/modules/health_stock/exceptions.py
trytond/modules/health_stock/health_stock.py
trytond/modules/health_stock/health_stock_view.xml
trytond/modules/health_stock/icons/tryton-inventory.svg
trytond/modules/health_stock/locale/ar.po
trytond/modules/health_stock/locale/de.po
trytond/modules/health_stock/locale/el.po
trytond/modules/health_stock/locale/eo.po
trytond/modules/health_stock/locale/es.po
trytond/modules/health_stock/locale/fr.po
trytond/modules/health_stock/locale/health_stock.pot
trytond/modules/health_stock/locale/it_IT.po
trytond/modules/health_stock/locale/ja_JP.po
trytond/modules/health_stock/locale/ka.po
trytond/modules/health_stock/locale/lo.po
trytond/modules/health_stock/locale/pt_BR.po
trytond/modules/health_stock/locale/sv.po
trytond/modules/health_stock/locale/tr.po
trytond/modules/health_stock/locale/uk.po
trytond/modules/health_stock/locale/zh_CN.po
trytond/modules/health_stock/pyproject.toml
trytond/modules/health_stock/tests/__init__.py
trytond/modules/health_stock/tests/test_health_stock.py
trytond/modules/health_stock/tryton.cfg
trytond/modules/health_stock/view/create_prescription_stock_move.xml
trytond/modules/health_stock/view/create_vaccination_stock_move.xml
trytond/modules/health_stock/view/lot_form.xml
trytond/modules/health_stock/view/lot_tree.xml
trytond/modules/health_stock/view/move_form.xml
trytond/modules/health_stock/view/move_tree.xml
trytond/modules/health_stock/view/party_form.xml
trytond/modules/health_stock/view/vaccination_form.xml
trytond/modules/health_stock/wizard/__init__.py
trytond/modules/health_stock/wizard/create_prescription_stock_move.xml
trytond/modules/health_stock/wizard/create_vaccination_stock_move.xml
gnuhealth_stock-5.0.2.dist-info/METADATA
gnuhealth_stock-5.0.2.dist-info/WHEEL
gnuhealth_stock-5.0.2.dist-info/licenses/COPYING
gnuhealth_stock-5.0.2.dist-info/RECORD
